{
  "Palette": "Elle",
  "Map Buildings": "true",
  "Alex's House": "true",
  "Elliot's House": "true",
  "Emily and Haley's House": "true",
  "Leah's House": "true",
  "Linus's Tent": "true",
  "Mayor Lewis's House": "true",
  "Pam's Trailer": "true",
  "Pam's House Upgrade": "true",
  "Sam's House": "true",
  "Adventurer's Guild": "true",
  "Blacksmith Shop": "true",
  "Carpenter Shop": "true",
  "Fish Shop": "true",
  "Marnie's Ranch": "true",
  "Pierre's General Store and Clinic": "true",
  "Stardrop Saloon": "true",
  "Bathhouse": "true",
  "Bus": "true",
  "Dusty's Doghouse": "true",
  "Hat Mouse House": "true",
  "Community Center Incomplete": "true",
  "Community Center Complete": "true",
  "Jojamart": "true",
  "Movie Theatre": "true",
  "Museum and Library": "true",
  "Oasis Shop": "true",
  "Railroad Station": "true",
  "Witch's Hut": "true",
  "Wizard's Tower": "true"
}